{
  "west": {
    "cells": [
      "8429a1dffffffff",
      "8428309ffffffff",
      "8428d55ffffffff",
      "8429b6dffffffff",
      "8429a41ffffffff",
      "8428f01ffffffff",
      "842986bffffffff",
      "842832bffffffff",
      "8429891ffffffff",
      "8448d89ffffffff",
      "8428d5dffffffff",
      "8428843ffffffff",
      "8429a0bffffffff",
      "8429a03ffffffff",
      "8429a15ffffffff",
      "8429a11ffffffff",
      "8429a19ffffffff",
      "8429a57ffffffff",
      "8428347ffffffff",
      "842830dffffffff",
      "8428301ffffffff",
      "842830bffffffff",
      "8428355ffffffff",
      "8428343ffffffff",
      "8428d43ffffffff",
      "8428d09ffffffff",
      "8428d0bffffffff",
      "8428d57ffffffff",
      "8428d51ffffffff",
      "8448ebbffffffff",
      "8448eb3ffffffff",
      "8429b65ffffffff",
      "8429b61ffffffff",
      "8429b69ffffffff",
      "8448e97ffffffff",
      "8429a4dffffffff",
      "8429a45ffffffff",
      "8429a47ffffffff",
      "8429a43ffffffff",
      "8429a4bffffffff"
    ]
  },
  "pacific": {
    "cells": [
      "84464b9ffffffff",
      "845d115ffffffff",
      "845d16bffffffff",
      "84464e1ffffffff",
      "840c733ffffffff",
      "840c739ffffffff",
      "840d5a9ffffffff",
      "840c455ffffffff",
      "840c641ffffffff",
      "840c0c7ffffffff",
      "840c74dffffffff",
      "840c731ffffffff",
      "840c559ffffffff",
      "840c465ffffffff",
      "840c46dffffffff",
      "840c73bffffffff",
      "840c707ffffffff",
      "840c73dffffffff",
      "840c715ffffffff",
      "840c703ffffffff",
      "840d5e7ffffffff",
      "840d5adffffffff",
      "840d5a1ffffffff",
      "840d5abffffffff",
      "840d585ffffffff",
      "840d5e3ffffffff",
      "840c443ffffffff",
      "840c409ffffffff",
      "840c40bffffffff",
      "840c457ffffffff",
      "840c451ffffffff",
      "840c45dffffffff",
      "840c64dffffffff",
      "840c645ffffffff",
      "840c647ffffffff",
      "840c643ffffffff",
      "840c64bffffffff",
      "840c649ffffffff",
      "840c0c5ffffffff",
      "840c0ebffffffff"
    ]
  },
  "mountain": {
    "cells": [
      "84268cdffffffff",
      "842696bffffffff",
      "8426905ffffffff",
      "8412db3ffffffff",
      "84288adffffffff",
      "842886dffffffff",
      "8428b1dffffffff",
      "8428b23ffffffff",
      "8428949ffffffff",
      "84268c7ffffffff",
      "842626dffffffff",
      "842600bffffffff",
      "84278b1ffffffff",
      "8426b0bffffffff",
      "842681bffffffff",
      "8426813ffffffff",
      "84268c5ffffffff",
      "84268c1ffffffff",
      "84268c9ffffffff",
      "8426aa7ffffffff",
      "8426969ffffffff",
      "8426963ffffffff",
      "842690dffffffff",
      "8426947ffffffff",
      "8426945ffffffff",
      "8426929ffffffff",
      "842692bffffffff",
      "8426907ffffffff",
      "8426901ffffffff",
      "8428841ffffffff",
      "8428847ffffffff",
      "8428809ffffffff",
      "8428855ffffffff",
      "842885dffffffff",
      "842884bffffffff",
      "8412db1ffffffff",
      "8412db7ffffffff",
      "84288a7ffffffff",
      "842899bffffffff",
      "8428993ffffffff"
    ]
  },
  "midwest": {
    "cells": [
      "842664dffffffff",
      "8427527ffffffff",
      "842a957ffffffff",
      "842661bffffffff",
      "842640dffffffff",
      "8426561ffffffff",
      "8427581ffffffff",
      "84260e3ffffffff",
      "84260d9ffffffff",
      "8427593ffffffff",
      "8427525ffffffff",
      "842621bffffffff",
      "84262cdffffffff",
      "84262c9ffffffff",
      "8427523ffffffff",
      "8427521ffffffff",
      "84274d3ffffffff",
      "84275d7ffffffff",
      "8427599ffffffff",
      "842ab31ffffffff",
      "842ab3bffffffff",
      "842ab15ffffffff",
      "842a955ffffffff",
      "842a90bffffffff",
      "842a91dffffffff",
      "842a919ffffffff",
      "842a953ffffffff",
      "842a951ffffffff",
      "8426619ffffffff",
      "8426611ffffffff",
      "8426613ffffffff",
      "84266cdffffffff",
      "842a927ffffffff",
      "842a925ffffffff",
      "842646bffffffff",
      "8426463ffffffff",
      "8426405ffffffff",
      "8426401ffffffff",
      "8426409ffffffff",
      "8426447ffffffff"
    ]
  },
  "south": {
    "cells": [
      "8426cb9ffffffff",
      "8444c1bffffffff",
      "842aa85ffffffff",
      "842a107ffffffff",
      "84264d1ffffffff",
      "8444dabffffffff",
      "842a135ffffffff",
      "842a307ffffffff",
      "842a8d9ffffffff",
      "8426c87ffffffff",
      "8426cbdffffffff",
      "8426cb1ffffffff",
      "8426cbbffffffff",
      "8426c95ffffffff",
      "8426c83ffffffff",
      "8444c19ffffffff",
      "8444c11ffffffff",
      "8444c13ffffffff",
      "8444ccdffffffff",
      "8444ea7ffffffff",
      "8444ea5ffffffff",
      "8444a1dffffffff",
      "8444a15ffffffff",
      "8444a17ffffffff",
      "842aae3ffffffff",
      "842aaa9ffffffff",
      "842aaabffffffff",
      "842aa87ffffffff",
      "842aa81ffffffff",
      "842aa8dffffffff",
      "842a105ffffffff",
      "842a12bffffffff",
      "842a13dffffffff",
      "842a139ffffffff",
      "842a103ffffffff",
      "842a101ffffffff",
      "84489a9ffffffff",
      "8448985ffffffff",
      "844898dffffffff",
      "84264ddffffffff"
    ]
  }
}
